jupyter-converter/__init__.py
jupyter-converter/cells.py
jupyter-converter/converter.py
jupyter_converter/__init__.py
jupyter_converter/cells.py
jupyter_converter/converter.py
jupyter_converter-0.0.8.dist-info/METADATA
jupyter_converter-0.0.8.dist-info/WHEEL
jupyter_converter-0.0.8.dist-info/top_level.txt
jupyter_converter-0.0.8.dist-info/RECORD
