Metadata-Version: 2.1
Name: jupyter-converter
Version: 0.0.8
Summary: Jupyter Notebook exam generator written by TeddyNote
Home-page: https://github.com/teddylee777
Author: teddylee777
Author-email: teddylee777@gmail.com
Keywords: teddynote,teddylee777,jupyter notebook converter,exam generator
Classifier: Programming Language :: Python :: 3.6
Classifier: Programming Language :: Python :: 3.7
Classifier: Programming Language :: Python :: 3.8
Classifier: Programming Language :: Python :: 3.9
Classifier: Programming Language :: Python :: 3.10
Classifier: Programming Language :: Python :: 3.11
Requires-Python: >=3.6
